README.md
setup.py
imctrans/__init__.py
imctrans/cli.py
imctrans.egg-info/PKG-INFO
imctrans.egg-info/SOURCES.txt
imctrans.egg-info/dependency_links.txt
imctrans.egg-info/entry_points.txt
imctrans.egg-info/not-zip-safe
imctrans.egg-info/top_level.txt
imctrans/cpp/__init__.py
imctrans/cpp/base.py
imctrans/cpp/blob.py
imctrans/cpp/code.py
imctrans/cpp/tests.py
imctrans/cpp/utils.py
imctrans/cpp/assets/src/IMC/Base/ByteBuffer.hpp
imctrans/cpp/assets/src/IMC/Base/ByteCopy.hpp
imctrans/cpp/assets/src/IMC/Base/CRC16.hpp
imctrans/cpp/assets/src/IMC/Base/Clock.hpp
imctrans/cpp/assets/src/IMC/Base/Config.hpp
imctrans/cpp/assets/src/IMC/Base/Exceptions.hpp
imctrans/cpp/assets/src/IMC/Base/Factory.cpp
imctrans/cpp/assets/src/IMC/Base/Factory.hpp
imctrans/cpp/assets/src/IMC/Base/InlineMessage.hpp
imctrans/cpp/assets/src/IMC/Base/JSON.hpp
imctrans/cpp/assets/src/IMC/Base/Message.hpp
imctrans/cpp/assets/src/IMC/Base/MessageList.hpp
imctrans/cpp/assets/src/IMC/Base/Packet.hpp
imctrans/cpp/assets/src/IMC/Base/Parser.hpp
imctrans/cpp/assets/src/IMC/Base/Platform.hpp
imctrans/cpp/assets/src/IMC/Base/Serialization.hpp
imctrans/cpp/assets/src/IMC/Base/String.hpp