Metadata-Version: 1.2
Name: imctrans
Version: 0.1.6
Summary: IMC Bindings Generator
Home-page: http://github.com/oceanscan/imctrans
Author: Ricardo Martins
Author-email: rasm@oceanscan-mst.com
License: Apache Software License (http://www.apache.org/licenses/LICENSE-2.0)
Platform: UNKNOWN
Classifier: Development Status :: 4 - Beta
Classifier: Topic :: Software Development :: Code Generators
Classifier: License :: OSI Approved :: Apache Software License
Classifier: Programming Language :: Python :: 3
Classifier: Programming Language :: Python :: 3.3
Classifier: Programming Language :: Python :: 3.4
Classifier: Programming Language :: Python :: 3.5
Classifier: Programming Language :: Python :: 3.6
Requires-Python: >=3.4
